Metadata-Version: 2.1
Name: tellosync
Version: 0.1.0
Summary: An easy framework to support DJI Tello scripting in Python 3
Home-page: https://github.com/vwu1888/easyTello
Author: Ezra Fielding, Vincent Wu
Author-email: ezra.fielding@gmail.com, vwu1888@gmail.com
License: UNKNOWN
Platform: UNKNOWN
Classifier: Programming Language :: Python :: 3
Classifier: License :: OSI Approved :: MIT License
Classifier: Operating System :: OS Independent
License-File: LICENSE
